tests/__init__.py
tgbot/LICENSE.txt
tgbot/README.md
tgbot/__init__.py
tgbot/basicapi/__init__.py
tgbot/basicapi/commands/__init__.py
tgbot/basicapi/decorator/__init__.py
tgbot/basicapi/decorator/tgcommands.py
tgbot/basicapi/http/__init__.py
tgbot/basicapi/http/httprequestcontroller.py
tgbot/basicapi/model/__init__.py
tgbot/basicapi/model/audio.py
tgbot/basicapi/model/base.py
tgbot/basicapi/model/chat.py
tgbot/basicapi/model/chatType.py
tgbot/basicapi/model/contact.py
tgbot/basicapi/model/document.py
tgbot/basicapi/model/inlineArticle.py
tgbot/basicapi/model/inlineGif.py
tgbot/basicapi/model/inlineObject.py
tgbot/basicapi/model/inlinePhoto.py
tgbot/basicapi/model/inlineQuery.py
tgbot/basicapi/model/location.py
tgbot/basicapi/model/message.py
tgbot/basicapi/model/sticker.py
tgbot/basicapi/model/user.py
tgbot/basicapi/model/video.py
tgbot/basicapi/parser/__init__.py
tgbot/basicapi/parser/commandparser.py
tgbot/basicapi/parser/inlineparser.py
tgbot/basicapi/parser/textparser.py
tgbot/basicapi/wsgi/__init__.py
tgbot/config/__init__.py
tgbot/config/jsonconfigreader.py
tgbot/config/ninegagapiparser.py
tgbot/config/tgbotconfigparser.py
tgbot/config/tgbotfileidparser.py
tgbot/resources/__init__.py
tgbot/resources/config/__init__.py
tgbot/resources/config/basicconfig.ini
tgbot/resources/emoji/__init__.py
tgbot/tglogging/__init__.py
tgbot/tgredis/__init__.py
tgbot-0.31.dist-info/DESCRIPTION.rst
tgbot-0.31.dist-info/METADATA
tgbot-0.31.dist-info/RECORD
tgbot-0.31.dist-info/WHEEL
tgbot-0.31.dist-info/metadata.json
tgbot-0.31.dist-info/top_level.txt
