Metadata-Version: 2.0
Name: tgbot
Version: 0.31
Summary: Framework to build a Telegram Bot based on a UWSGI Server
Home-page: https://github.com/T-Eberle/tgbot/
Author: Thomas Eberle
Author-email: Thomas@tommyelroy.com
License: The MIT License (MIT)
Requires-Dist: feedparser (>=5.2.1)
Requires-Dist: pytz (>=2015.4)
Requires-Dist: redis (>=2.10.3)
Requires-Dist: requests (>=2.7.0)
Requires-Dist: setuptools (>=18.3.1)
Requires-Dist: uwsgidecorators (>=1.1.0)
